templateman/__init__.py
templateman/__main__.py
templateman/cli.py
templateman-1.0.0.dist-info/LICENSE
templateman-1.0.0.dist-info/METADATA
templateman-1.0.0.dist-info/WHEEL
templateman-1.0.0.dist-info/top_level.txt
templateman-1.0.0.dist-info/RECORD
